replicate_batch_process/__init__.py
replicate_batch_process/config.py
replicate_batch_process/example_usage.py
replicate_batch_process/init_environment.py
replicate_batch_process/intelligent_batch_processor.py
replicate_batch_process/main.py
replicate_batch_process-1.1.1.dist-info/licenses/LICENSE
replicate_batch_process-1.1.1.dist-info/METADATA
replicate_batch_process-1.1.1.dist-info/WHEEL
replicate_batch_process-1.1.1.dist-info/entry_points.txt
replicate_batch_process-1.1.1.dist-info/top_level.txt
replicate_batch_process-1.1.1.dist-info/RECORD
