Metadata-Version: 2.4
Name: replicate-batch-process
Version: 1.1.1
Summary: Intelligent batch processing tool for Replicate models with automatic fallback mechanisms
Home-page: https://github.com/preangelleo/replicate_batch_process
Author: preangelleo
Author-email: 
Maintainer: preangelleo
License: MIT
Project-URL: Homepage, https://github.com/preangelleo/replicate_batch_process
Project-URL: Documentation, https://github.com/preangelleo/replicate_batch_process#readme
Project-URL: Repository, https://github.com/preangelleo/replicate_batch_process.git
Project-URL: Bug Reports, https://github.com/preangelleo/replicate_batch_process/issues
Project-URL: Changelog, https://github.com/preangelleo/replicate_batch_process/releases
Keywords: replicate,ai,batch-processing,image-generation,machine-learning,api-client,fallback-mechanism,concurrent-processing
Classifier: Development Status :: 5 - Production/Stable
Classifier: Intended Audience :: Developers
Classifier: Topic :: Software Development :: Libraries :: Python Modules
Classifier: Topic :: Scientific/Engineering :: Artificial Intelligence
Classifier: Topic :: Multimedia :: Graphics
Classifier: License :: OSI Approved :: MIT License
Classifier: Programming Language :: Python :: 3
Classifier: Programming Language :: Python :: 3.8
Classifier: Programming Language :: Python :: 3.9
Classifier: Programming Language :: Python :: 3.10
Classifier: Programming Language :: Python :: 3.11
Classifier: Programming Language :: Python :: 3.12
Classifier: Operating System :: OS Independent
Requires-Python: >=3.8
License-File: LICENSE
Requires-Dist: replicate>=0.15.0
Requires-Dist: requests>=2.25.0
Requires-Dist: asyncio-throttle>=1.0.2
Requires-Dist: python-dotenv>=0.19.0
Provides-Extra: dev
Requires-Dist: pytest>=6.0; extra == "dev"
Requires-Dist: pytest-asyncio>=0.21.0; extra == "dev"
Requires-Dist: black>=22.0; extra == "dev"
Requires-Dist: flake8>=4.0; extra == "dev"
Requires-Dist: mypy>=0.950; extra == "dev"
Provides-Extra: test
Requires-Dist: pytest>=6.0; extra == "test"
Requires-Dist: pytest-asyncio>=0.21.0; extra == "test"
Dynamic: home-page
Dynamic: license-file
Dynamic: requires-python
